{
  "config": {
    "seed": 42,
    "data": {
      "data_dir": "./data",
      "batch_size": 32,
      "num_workers": 0,
      "val_split": 0.1
    },
    "model": {
      "num_classes": 100,
      "freeze_backbone": false,
      "image_size": 224
    },
    "optimizer": {
      "lr": 0.001,
      "momentum": 0.9,
      "weight_decay": 0
    },
    "logging": {
      "log_dir": "./results/logs",
      "eval_every": 10,
      "checkpoint_every": 50,
      "checkpoint_dir": "./results/checkpoints/fedavg",
      "output_dir": "./results/outputs/fedavg"
    },
    "experiment_name": "most_sensitive_s0_9_cal3",
    "federated": {
      "num_clients": 100,
      "participation_rate": 0.1,
      "local_steps": 3,
      "num_rounds": 500,
      "sharding": "non_iid",
      "num_classes_per_client": 10,
      "use_sparse": true,
      "sparse_strategy": "most_sensitive",
      "sparsity_level": 0.9,
      "num_calibration_rounds": 3,
      "alpha": 0.4
    }
  },
  "history": {
    "round": [
      10,
      20,
      30,
      40,
      50,
      60,
      70,
      80,
      90,
      100,
      110,
      120,
      130,
      140,
      150,
      160,
      170,
      180,
      190,
      200,
      210,
      220,
      230,
      240,
      250,
      260,
      270,
      280,
      290,
      300,
      310,
      320,
      330,
      340,
      350,
      360,
      370,
      380,
      390,
      400,
      410,
      420,
      430,
      440,
      450,
      460,
      470,
      480,
      490,
      500
    ],
    "val_loss": [
      3.6539389526367185,
      3.5385644912719725,
      3.466650461959839,
      3.4162409957885744,
      3.380404372024536,
      3.3429426307678223,
      3.3042171211242675,
      3.2757817337036133,
      3.243804895401001,
      3.2191085388183596,
      3.1910009006500246,
      3.1662134014129637,
      3.1404128524780273,
      3.111798181915283,
      3.095131294631958,
      3.0732958793640135,
      3.051568936920166,
      3.0320417072296144,
      3.0162938426971437,
      2.992937533569336,
      2.9735288707733156,
      2.9564767665863037,
      2.941372193145752,
      2.9231834968566894,
      2.9024807807922364,
      2.898694318008423,
      2.8798379878997804,
      2.8587580757141113,
      2.8467743144989015,
      2.828441215133667,
      2.8169794368743895,
      2.8030132328033446,
      2.780998207092285,
      2.7756624858856203,
      2.7607231090545654,
      2.7440333137512205,
      2.738818699645996,
      2.7189979084014895,
      2.7137578433990477,
      2.7036185054779054,
      2.6894531032562257,
      2.682407243347168,
      2.6669567070007325,
      2.652787397003174,
      2.646154932785034,
      2.6339006050109863,
      2.621257434082031,
      2.6146391902923583,
      2.5942724365234375,
      2.5964871868133543
    ],
    "val_acc": [
      0.7352,
      0.744,
      0.7506,
      0.752,
      0.7526,
      0.75,
      0.7472,
      0.749,
      0.7604,
      0.7508,
      0.7476,
      0.7516,
      0.7516,
      0.7606,
      0.756,
      0.7524,
      0.7488,
      0.7616,
      0.7578,
      0.7614,
      0.763,
      0.7674,
      0.766,
      0.7754,
      0.7728,
      0.7726,
      0.7736,
      0.7802,
      0.7846,
      0.7858,
      0.781,
      0.787,
      0.7928,
      0.7892,
      0.7872,
      0.7886,
      0.7844,
      0.7936,
      0.7878,
      0.7904,
      0.7882,
      0.7936,
      0.7932,
      0.7914,
      0.7972,
      0.801,
      0.798,
      0.8006,
      0.8056,
      0.7966
    ]
  },
  "final_val_acc": 0.7966,
  "final_test_loss": 2.612287553405762,
  "final_test_acc": 0.7863
}